sdhash_wrapper/__init__.py
sdhash_wrapper/wrapper.py
sdhash_wrapper-0.1.0.dist-info/licenses/LICENSE
sdhash_wrapper-0.1.0.dist-info/METADATA
sdhash_wrapper-0.1.0.dist-info/WHEEL
sdhash_wrapper-0.1.0.dist-info/entry_points.txt
sdhash_wrapper-0.1.0.dist-info/top_level.txt
sdhash_wrapper-0.1.0.dist-info/RECORD
