Metadata-Version: 2.4
Name: sdhash_wrapper
Version: 0.1.0
Summary: A Python wrapper for SDHash binary.
Home-page: https://github.com/Botacin-s-Lab/SDhash_Python
Author: Your Name
Author-email: mabonmn2002@gmail.com
License: MIT
Classifier: Programming Language :: Python :: 3
Classifier: License :: OSI Approved :: MIT License
Classifier: Operating System :: OS Independent
Requires-Python: >=3.6
License-File: LICENSE
Dynamic: author
Dynamic: author-email
Dynamic: classifier
Dynamic: description
Dynamic: description-content-type
Dynamic: home-page
Dynamic: license
Dynamic: license-file
Dynamic: requires-python
Dynamic: summary
